{
  "id": "ST-00001",
  "title": "Snake game",
  "currentStep": "Done",
  "createdAt": "2026-04-16T10:00:35.576Z",
  "updatedAt": "2026-04-16T21:31:02.000Z",
  "baseCommit": "136c061d2ac09b098290c46e440eaffd68ba8a93",
  "branchName": "story/ST-00001",
  "targetBranchName": "main",
  "lastImplementationCommit": "9b15a1d2f1b14fd1ad5b5d580f4b06c5b98f4b3e",
  "mergeCommit": "4bc364fd509f4f0fb5c8ba59e2fd15fd3e2af1b0",
  "mergedAt": "2026-04-16T21:31:02.000Z",
  "reviewLoops": 2,
  "acceptedAt": {
    "Draft": "2026-04-16T10:21:25.131Z",
    "Plan": "2026-04-16T11:14:32.296Z",
    "Implementation": "2026-04-16T21:26:59.153Z",
    "Review": "2026-04-16T21:28:10.000Z",
    "Documentation": "2026-04-16T21:29:00.000Z",
    "Merge": "2026-04-16T21:31:02.000Z"
  },
  "lastRunAt": {
    "Draft": "2026-04-16T10:17:10.000Z",
    "Plan": "2026-04-16T11:18:21.591Z",
    "Implementation": "2026-04-16T21:26:39.835Z",
    "Review": "2026-04-16T21:27:30.336Z",
    "Documentation": "2026-04-16T21:28:42.000Z",
    "Merge": "2026-04-16T21:31:02.000Z"
  },
  "changedFiles": [],
  "specFilesTouched": [
    "doc/spec/overview.md"
  ],
  "reviewVerdict": "approved",
  "runHistoryVersion": 1,
  "latestRunByStep": {
    "Draft": "20260416T101710000Z-sample",
    "Plan": "20260416T111821591Z-sample",
    "Implementation": "20260416T212639835Z-sample",
    "Review": "20260416T212730336Z-sample",
    "Documentation": "20260416T212842000Z-sample",
    "Merge": "20260416T213102000Z-sample"
  },
  "acceptedRunByStep": {
    "Draft": "20260416T101710000Z-sample",
    "Plan": "20260416T111821591Z-sample",
    "Implementation": "20260416T212639835Z-sample",
    "Review": "20260416T212730336Z-sample",
    "Documentation": "20260416T212842000Z-sample",
    "Merge": "20260416T213102000Z-sample"
  },
  "artifactHashByStep": {
    "Draft": "6c09145b7b96211d7d9f426bdb11c02dc49ff740a868554587d35fdfeb5a0aba",
    "Plan": "f7f3d252751d2e259ad10694636516ec31946064a3a3b08483b8cd79702022f8",
    "Implementation": "fd4ccf36732230774b002959979349362ce3e5660d162f4666044bbeecaa7df5",
    "Review": "32aa46fa2799bb414d89f8481ca3c0fa13e2ed7339b4f66f5eae82c09b0ad027",
    "Documentation": "b0d206ab058ae1c2c6f10691ad0f344be9cc48dec9572eace65b6b6b47b6f3f0",
    "Merge": "0d4adb152422903475eff6bf71ee93f586ee26b3b11f24faa5c4d21cbb330988"
  },
  "lastRunStatusByStep": {
    "Draft": "accepted",
    "Plan": "accepted",
    "Implementation": "accepted",
    "Review": "accepted",
    "Documentation": "accepted",
    "Merge": "accepted"
  }
}
